{
  "tipo": "acciaio",
  "offensivo": {
    "superefficace": [
      "roccia",
      "ghiaccio",
      "folletto"
    ],
    "poco_efficace": [
      "acciaio",
      "fuoco",
      "acqua",
      "elettro"
    ],
    "inefficace": []
  },
  "diffensivo": {
    "superefficace": [
      "lotta",
      "terra",
      "fuoco"
    ],
    "poco_efficace": [
      "normale",
      "volante",
      "roccia",
      "coleottero",
      "acciaio",
      "erba",
      "psico",
      "ghiaccio",
      "drago",
      "folletto"
    ],
    "inefficace": [
      "veleno"
    ]
  }
}