[
  {
    "voce": "Poiché la bianca pelliccia è coperta da una patina di grasso speciale, i colpi dei nemici vengono deviati.",
    "giochi": [
      "nero"
    ]
  },
  {
    "voce": "La sua pelliccia bianca è morbidissima al tatto. Non accumula né polvere né elettricità statica.",
    "giochi": [
      "bianco",
      "x",
      "rubino_omega"
    ]
  },
  {
    "voce": "Il suo corpo è ricoperto di un grasso speciale sul quale scivolano via i colpi e i pugni dell'avversario.",
    "giochi": [
      "nero_2",
      "bianco_2",
      "y",
      "zaffiro_alpha"
    ]
  }
]