[
  {
    "voce": "CRADILY scandaglia i fondali oceanici in cerca di nutrimento. Riesce ad estendere il collo, simile al tronco di un albero, per catturare ignare prede con i propri otto tentacoli.",
    "giochi": [
      "rubino",
      "rubino_omega"
    ]
  },
  {
    "voce": "Il corpo di CRADILY funge da ancora, per evitare di essere spazzato via dal mare grosso. Il POKéMON secerne un potente liquido digestivo dai propri tentacoli.",
    "giochi": [
      "zaffiro",
      "zaffiro_alpha"
    ]
  },
  {
    "voce": "CRADILY trascina il suo pesante corpo sul fondo marino e costruisce il nido nei caldi bassifondi del mare. Con la bassa marea, si può vedere il POKéMON sulle spiagge.",
    "giochi": [
      "smeraldo"
    ]
  },
  {
    "voce": "Irretisce la preda con gli otto tentacoli, poi la scioglie usando un forte acido e, infine, se ne ciba.",
    "giochi": [
      "rosso_fuoco",
      "verde_foglia",
      "y"
    ]
  },
  {
    "voce": "Vive in acque poco profonde nei mari caldi. Con la bassa marea, scava sulla riva in cerca di prede.",
    "giochi": [
      "diamante",
      "perla",
      "platino",
      "nero",
      "bianco",
      "nero_2",
      "bianco_2",
      "x"
    ]
  },
  {
    "voce": "Vive nei mari caldi. Usa il corpo per ancorarsi al fondo marino anche quando il mare è mosso.",
    "giochi": [
      "heartgold",
      "soulsilver"
    ]
  }
]