[
  {
    "voce": "Si costruisce il nido con le ossa raccolte. Afferra le prede indebolite con gli arti e le trasporta nel nido.",
    "giochi": [
      "nero"
    ]
  },
  {
    "voce": "Osserva la terra dal cielo e si lancia sulle prede in difficoltà. Ha l'abitudine di farsi delle decorazioni con le ossa.",
    "giochi": [
      "bianco",
      "y",
      "zaffiro_alpha"
    ]
  },
  {
    "voce": "Vola in cerchio nel cielo e quando scorge una preda le si lancia contro in picchiata per trasportarla al suo nido.",
    "giochi": [
      "nero_2",
      "bianco_2",
      "x",
      "rubino_omega"
    ]
  }
]