[
  {
    "voce": "Si indebolisce quando il corpo si secca. Previene l'essiccazione avvolgendosi in molti strati di sottili membrane.",
    "giochi": [
      "nero",
      "y",
      "zaffiro_alpha"
    ]
  },
  {
    "voce": "Liberatosi della pesante conchiglia, è diventato leggero. Lotta con le movenze proprie di un ninja.",
    "giochi": [
      "bianco",
      "x",
      "rubino_omega"
    ]
  },
  {
    "voce": "Si indebolisce se il suo corpo si secca. Lotta avvolto in una membrana protettiva spruzzando un liquido velenoso.",
    "giochi": [
      "nero_2",
      "bianco_2"
    ]
  }
]