[
  {
    "voce": "Accumula nelle membrane l'elettricità che produce all'interno delle guance, poi la rilascia planando.",
    "giochi": [
      "nero",
      "y",
      "zaffiro_alpha"
    ]
  },
  {
    "voce": "Vive nelle foreste sulle cime degli alberi. Plana usando una membrana simile a un mantello, elettrificata all'interno.",
    "giochi": [
      "bianco",
      "x",
      "rubino_omega"
    ]
  },
  {
    "voce": "Vola usando la sua membrana e fulmina il nemico con l'energia accumulata nelle fossette elettriche sulle sue guance.",
    "giochi": [
      "nero_2",
      "bianco_2"
    ]
  }
]